<annotation>
	<folder>Diego Three Seater Sofa in Denim Blue Colour by CasaCraft</folder>
	<filename>Diego Three Seater Sofa in Denim Blue Colour by CasaCraft-8.jpg</filename>
	<path>D:\Projects\ObjectDetection\development\Scraper\development\images\Three Seater Sofas\Diego Three Seater Sofa in Denim Blue Colour by CasaCraft\Diego Three Seater Sofa in Denim Blue Colour by CasaCraft-8.jpg</path>
	<source>
		<database>Unknown</database>
	</source>
	<size>
		<width>1600</width>
		<height>800</height>
		<depth>3</depth>
	</size>
	<segmented>0</segmented>
	<object>
		<name>Diego Three Seater Sofa in Denim Blue Colour by CasaCraft</name>
		<pose>Unspecified</pose>
		<truncated>0</truncated>
		<difficult>0</difficult>
		<bndbox>
			<xmin>124</xmin>
			<ymin>16</ymin>
			<xmax>1489</xmax>
			<ymax>745</ymax>
		</bndbox>
	</object>
</annotation>
